{
  "userList": [
    {
      "Hesab nomresi": 111,
      "Ad": "Farid",
      "Soyad": "Ahmadov",
      "Depozit": 29162
    },
    {
      "Hesab nomresi": 222,
      "Ad": "Nurlan",
      "Soyad": "Aliyev",
      "Depozit": 1033
    },
    {
      "Hesab nomresi": 333,
      "Ad": "Yasin",
      "Soyad": "Ugur",
      "Depozit": 2000
    },
    {
      "Hesab nomresi": 444,
      "Ad": "Samir",
      "Soyad": "Karimov",
      "Depozit": 1500
    },
    {
      "Hesab nomresi": 555,
      "Ad": "Ali",
      "Soyad": "Aliyev",
      "Depozit": 800
    },
    {
      "Hesab nomresi": 123,
      "Ad": "Nuru",
      "Soyad": "Penahov",
      "Depozit": 777
    },
    {
      "Hesab nomresi": 555,
      "Ad": "dsd",
      "Soyad": "ssf",
      "Depozit": 222
    },
    {
      "Hesab nomresi": 555,
      "Ad": "sdasd",
      "Soyad": "asdad",
      "Depozit": 888
    },
    {
      "Hesab nomresi": 888,
      "Ad": "adad",
      "Soyad": "adad",
      "Depozit": 22
    },
    {
      "Hesab nomresi": 222,
      "Ad": "dsd",
      "Soyad": "sdsd",
      "Depozit": 232
    },
    {
      "Hesab nomresi": 258,
      "Ad": "Farid",
      "Soyad": "Xan",
      "Depozit": 1499
    },
    {
      "Hesab nomresi": 111,
      "Ad": "ada",
      "Soyad": "adad",
      "Depozit": 222
    },
    {
      "Hesab nomresi": 111,
      "Ad": "11",
      "Soyad": "11",
      "Depozit": 11
    },
    {
      "Hesab nomresi": 111,
      "Ad": "111",
      "Soyad": "1",
      "Depozit": 11
    },
    {
      "Hesab nomresi": 111,
      "Ad": "11",
      "Soyad": "1",
      "Depozit": 1
    },
    {
      "Hesab nomresi": 555,
      "Ad": "Ferod",
      "Soyad": "aaa",
      "Depozit": 2222
    },
    {
      "Hesab nomresi": 111,
      "Ad": "Frr",
      "Soyad": "fdff",
      "Depozit": 999
    },
    {
      "Hesab nomresi": 555,
      "Ad": "Farud",
      "Soyad": "Ahmad",
      "Depozit": 777
    },
    {
      "Hesab nomresi": 255,
      "Ad": "Nicat",
      "Soyad": "Quliyev",
      "Depozit": 900
    },
    {
      "Hesab nomresi": 789,
      "Ad": "Yasin",
      "Soyad": "Ugur",
      "Depozit": 150
    },
    {
      "Hesab nomresi": 897,
      "Ad": "Farid",
      "Soyad": "Akhmad",
      "Depozit": 700
    },
    {
      "Hesab nomresi": 987,
      "Ad": "Resul",
      "Soyad": "Rustemli",
      "Depozit": 7000
    },
    {
      "Hesab nomresi": 777,
      "Ad": "Fred",
      "Soyad": "Akh",
      "Depozit": 7888
    },
    {
      "Hesab nomresi": 879,
      "Ad": "asdad",
      "Soyad": "adad",
      "Depozit": 2222
    },
    {
      "Hesab nomresi": 234,
      "Ad": "sada",
      "Soyad": "adad",
      "Depozit": 852
    },
    {
      "Hesab nomresi": 456,
      "Ad": "adas",
      "Soyad": "ada",
      "Depozit": 222
    },
    {
      "Hesab nomresi": 345,
      "Ad": "sdd",
      "Soyad": "adad",
      "Depozit": 222
    },
    {
      "Hesab nomresi": 343,
      "Ad": "dfsf",
      "Soyad": "sfsf",
      "Depozit": 223
    },
    {
      "Hesab nomresi": 121,
      "Ad": "adad",
      "Soyad": "dada",
      "Depozit": 222
    },
    {
      "Hesab nomresi": 133,
      "Ad": "afs",
      "Soyad": "dfsdf",
      "Depozit": 233
    },
    {
      "Hesab nomresi": 232,
      "Ad": "sdd",
      "Soyad": "sdsd",
      "Depozit": 222
    },
    {
      "Hesab nomresi": 222,
      "Ad": "dsd",
      "Soyad": "sdsd",
      "Depozit": 2222
    },
    {
      "Hesab nomresi": 323,
      "Ad": "asd",
      "Soyad": "adad",
      "Depozit": 233
    },
    {
      "Hesab nomresi": 333,
      "Ad": "Yasin",
      "Soyad": "Ugur",
      "Depozit": 666
    },
    {
      "Hesab nomresi": 233,
      "Ad": "SDS",
      "Soyad": "sdad",
      "Depozit": 2222
    },
    {
      "Hesab nomresi": 222,
      "Ad": "sdd",
      "Soyad": "sdsd",
      "Depozit": 222
    },
    {
      "Hesab nomresi": 221,
      "Ad": "ssd",
      "Soyad": "af",
      "Depozit": 333
    },
    {
      "Hesab nomresi": 222,
      "Ad": "22ds",
      "Soyad": "sd",
      "Depozit": 222
    },
    {
      "Hesab nomresi": 222,
      "Ad": "sd",
      "Soyad": "dsd",
      "Depozit": 22
    },
    {
      "Hesab nomresi": 222,
      "Ad": "sdsd",
      "Soyad": "sdsd",
      "Depozit": 222
    },
    {
      "Hesab nomresi": 222,
      "Ad": "sdsd",
      "Soyad": "sdsd",
      "Depozit": 333
    },
    {
      "Hesab nomresi": 222,
      "Ad": "dsds",
      "Soyad": "sdsd",
      "Depozit": 333
    },
    {
      "Hesab nomresi": 555,
      "Ad": "sdsd",
      "Soyad": "sd",
      "Depozit": 333
    }
  ]
}